{
  "account": [
    {
      "createdAt": "09:32:48 GMT+0700 (WIB)",
      "updatedAt": "",
      "username": "nncrawler",
      "password": "nncrawler",
      "url": "github.com",
      "id": "HkFLawAkf"
    },
    {
      "createdAt": "Sun, 19 Nov 2017 04:27:02 GMT",
      "updatedAt": "",
      "username": "asd",
      "password": "asd",
      "url": "asd",
      "id": "By1QOY0Jf"
    },
    {
      "createdAt": "Sun, 19 Nov 2017 04:27:09 GMT",
      "updatedAt": "Sun, 19 Nov 2017 04:34:03 GMT",
      "username": "asdasd",
      "password": "asdasd",
      "url": "asdasd",
      "id": "r1SmdFCJf"
    }
  ]
}